{
  "kind": "collectionType",
  "collectionName": "categories",
  "info": {
    "singularName": "category",
    "pluralName": "categories",
    "displayName": "Category",
    "description": ""
  },
  "options": {
    "draftAndPublish": true
  },
  "pluginOptions": {},
  "attributes": {
    "Name": {
      "type": "string",
      "required": true
    },
    "Icon": {
      "type": "media",
      "multiple": false,
      "required": true,
      "allowedTypes": [
        "images",
        "files",
        "videos",
        "audios"
      ]
    },
    "stylists": {
      "type": "relation",
      "relation": "manyToMany",
      "target": "api::stylist.stylist",
      "mappedBy": "categories"
    }
  }
}
